odoo/addons/calendar_event_multi_company/README.rst
odoo/addons/calendar_event_multi_company/__init__.py
odoo/addons/calendar_event_multi_company/__manifest__.py
odoo/addons/calendar_event_multi_company/i18n/calendar_event_multi_company.pot
odoo/addons/calendar_event_multi_company/i18n/it.po
odoo/addons/calendar_event_multi_company/models/__init__.py
odoo/addons/calendar_event_multi_company/models/calendar_event.py
odoo/addons/calendar_event_multi_company/readme/CONTRIBUTORS.md
odoo/addons/calendar_event_multi_company/readme/DESCRIPTION.md
odoo/addons/calendar_event_multi_company/security/calendar_event.xml
odoo/addons/calendar_event_multi_company/static/description/icon.png
odoo/addons/calendar_event_multi_company/static/description/index.html
odoo/addons/calendar_event_multi_company/tests/__init__.py
odoo/addons/calendar_event_multi_company/tests/test_calendar_event.py
odoo/addons/calendar_event_multi_company/views/calendar_event.xml
odoo_addon_calendar_event_multi_company-18.0.1.0.0.2.dist-info/METADATA
odoo_addon_calendar_event_multi_company-18.0.1.0.0.2.dist-info/WHEEL
odoo_addon_calendar_event_multi_company-18.0.1.0.0.2.dist-info/top_level.txt
odoo_addon_calendar_event_multi_company-18.0.1.0.0.2.dist-info/RECORD
